mptools/__init__.py
mptools/command_line.py
mptools/dataformat.py
mptools/log.py
mptools/logger.py
mptools/timeformat.py
mptools/color/README.md
mptools/color/__init__.py
mptools/color/fader.py
mptools/color/loader.py
mptools/dbutils/__init__.py
mptools/dbutils/wiz.py
mptools/dbutils/adapters/__init__.py
mptools/dbutils/adapters/postgresql.py
mptools/dbutils/adapters/sqlite.py
mptools/frameworks/__init__.py
mptools/frameworks/py4web/__init__.py
mptools/frameworks/py4web/controller.py
mptools/frameworks/py4web/shampooform.py
mptools-1.0.10.dist-info/LICENSE
mptools-1.0.10.dist-info/METADATA
mptools-1.0.10.dist-info/WHEEL
mptools-1.0.10.dist-info/entry_points.txt
mptools-1.0.10.dist-info/top_level.txt
mptools-1.0.10.dist-info/RECORD
