Metadata-Version: 2.1
Name: mptools
Version: 1.0.10
Summary: A very custom collection of development shared libraries
Home-page: https://github.com/manuelep/mptools
Author: Manuele Pesenti
Author-email: manuele@inventati.org
License: UNKNOWN
Project-URL: Bug Tracker, https://github.com/manuelep/mptools/issues
Platform: UNKNOWN
Classifier: Programming Language :: Python :: 3
Classifier: License :: OSI Approved :: GNU General Public License v3 (GPLv3)
Classifier: Operating System :: OS Independent
Requires-Python: >=3.6
License-File: LICENSE
Requires-Dist: py4web
Requires-Dist: pandas
Requires-Dist: matplotlib
Requires-Dist: numpy
Requires-Dist: diskcache
Requires-Dist: pytopojson
